LICENSE
MANIFEST.in
README.rst
flask_rest.py
setup.py
Flask_REST.egg-info/PKG-INFO
Flask_REST.egg-info/SOURCES.txt
Flask_REST.egg-info/dependency_links.txt
Flask_REST.egg-info/requires.txt
Flask_REST.egg-info/top_level.txt