Metadata-Version: 1.0
Name: Flask-REST
Version: 1.1
Summary: A simple REST toolkit for Flask
Home-page: http://github.com/ametaireau/flask-rest/
Author: Alexis Métaireau
Author-email: alexis@notmyidea.org
License: BSD
Platform: UNKNOWN
Classifier: Environment :: Web Environment
Classifier: Intended Audience :: Developers
Classifier: License :: OSI Approved :: BSD License
Classifier: Operating System :: OS Independent
Classifier: Programming Language :: Python
Classifier: Topic :: Internet :: WWW/HTTP :: Dynamic Content
Classifier: Topic :: Software Development :: Libraries :: Python Modules
